Metadata-Version: 2.1
Name: scrapy-wayback
Version: 1.0.3
Summary: Scrapy middleware with wayback machine support for more robust scrapers.
Home-page: https://github.com/8W9aG/scrapy-wayback
Author: Will Sackfield
Author-email: will.sackfield@gmail.com
License: MIT
Keywords: scrapy middleware wayback
Platform: UNKNOWN
Classifier: License :: OSI Approved :: MIT License
Classifier: Programming Language :: Python :: 3
Classifier: Framework :: Scrapy
License-File: LICENSE
